q1pulse/__init__.py
q1pulse/instrument.py
q1pulse/program.py
q1pulse/turbo_cluster.py
q1pulse/assembler/__init__.py
q1pulse/assembler/generator.py
q1pulse/assembler/generator_data.py
q1pulse/assembler/instruction_queue.py
q1pulse/assembler/registers.py
q1pulse/lang/__init__.py
q1pulse/lang/base.py
q1pulse/lang/conditions.py
q1pulse/lang/exceptions.py
q1pulse/lang/flow_statements.py
q1pulse/lang/generator.py
q1pulse/lang/loops.py
q1pulse/lang/math_expressions.py
q1pulse/lang/register.py
q1pulse/lang/register_statements.py
q1pulse/lang/registers.py
q1pulse/lang/sequence.py
q1pulse/lang/simulator_statements.py
q1pulse/lang/timed_statements.py
q1pulse/lang/timeline.py
q1pulse/lang/triggers.py
q1pulse/modules/__init__.py
q1pulse/modules/modules.py
q1pulse/modules/sequencer_states.py
q1pulse/sequencer/__init__.py
q1pulse/sequencer/builderbase.py
q1pulse/sequencer/control.py
q1pulse/sequencer/readout.py
q1pulse/sequencer/sequencer.py
q1pulse/sequencer/sequencer_data.py
q1pulse/util/__init__.py
q1pulse/util/delayedkeyboardinterrupt.py
q1pulse/util/q1configuration.py
q1pulse/util/qblox_version.py
q1pulse-1.0.5.dist-info/licenses/LICENSE
q1pulse-1.0.5.dist-info/METADATA
q1pulse-1.0.5.dist-info/WHEEL
q1pulse-1.0.5.dist-info/top_level.txt
q1pulse-1.0.5.dist-info/RECORD
