Metadata-Version: 2.4
Name: q1pulse
Version: 1.0.5
Summary: Compiler for Qblox Q1ASM in Python.
Author-email: Sander de Snoo <s.l.desnoo@tudelft.nl>
License-Expression: MIT
Project-URL: Documentation, https://github.com/sldesnoo-Delft/q1pulse/blob/main/README.md
Project-URL: Repository, https://github.com/sldesnoo-Delft/q1pulse
Project-URL: Changelog, https://github.com/sldesnoo-Delft/q1pulse/blob/main/CHANGELOG.md
Classifier: Programming Language :: Python :: 3
Classifier: Operating System :: OS Independent
Requires-Python: >=3.10
License-File: LICENSE
Requires-Dist: numpy>=1.24
Requires-Dist: qblox_instruments
Dynamic: license-file
